xiaocTools/__init__.py
xiaocTools/xiaocTools.py
xiaocTools-0.0.2.dist-info/LICENSE
xiaocTools-0.0.2.dist-info/METADATA
xiaocTools-0.0.2.dist-info/WHEEL
xiaocTools-0.0.2.dist-info/top_level.txt
xiaocTools-0.0.2.dist-info/RECORD
